my_calc.py
my_calc-0.0.1.dist-info/METADATA
my_calc-0.0.1.dist-info/WHEEL
my_calc-0.0.1.dist-info/top_level.txt
my_calc-0.0.1.dist-info/RECORD
