Metadata-Version: 2.1
Name: my-calc
Version: 0.0.1
Summary: Calculator created with hillel group of 13.09.2021
Home-page: UNKNOWN
Author: Vadym
Author-email: v@mail.ru
License: UNKNOWN
Platform: UNKNOWN
Requires-Python: >=3.7
